[
  {
    "title": "Responsible Innovation: Israel's Policy on Artificial Intelligence Regulation and Ethics",
    "type": "policy_strategy",
    "date": "2023-12",
    "pages": "11"
  },
  {
    "title": "Israel National AI Program 2024: Shaping the Future",
    "type": "policy_strategy",
    "date": "2024",
    "pages": "13"
  },
  {
    "title": "National Program for Artificial Intelligence: Program and Snapshot \u2013 April 2025",
    "type": "policy_strategy",
    "date": "2025-04",
    "pages": "83"
  },
  {
    "title": "Privacy Protection Law, 5741-1981 (as amended to August 14, 2025 incl. Amendment 13)",
    "type": "binding_law_sectoral",
    "date": "1981-02-19",
    "pages": "18"
  }
]